s4/digital/fa.v
module fa(a, b, cin, s, cout);
input a, b, cin;
output s, cout;
assign s = a ^ b ^ cin;
assign cout = (a & b) | (b & cin) | (a & cin);
endmodule

module tb;
reg a, b, cin;
wire s, cout;
fa gate(a, b, cin, s, cout); 
initial begin
    $dumpfile("fa.vcd");
    $dumpvars(0, tb);
end
initial begin
    $monitor("a=%b,b=%b,cin=%b,s=%b,cout=%b", a, b, cin, s, cout); 
    a=0; b=0; cin=0;
    #10;
    a=0; b=0; cin=1;
    #10;
    a=0; b=1; cin=0;
    #10;
    a=0; b=1; cin=1;
    #10;
    a=1; b=0; cin=0;  
    #10;
    a=1; b=0; cin=1;
    #10;
    a=1; b=1; cin=0;
    #10;
    a=1; b=1; cin=1;
    #10;
    $finish();
end
endmodule

s4/digital/fa.vcd
$date
	Thu Jul 11 07:47:29 2024
$end
$version
	Icarus Verilog
$end
$timescale
	1s
$end
$scope module tb $end
$var wire 1 ! s $end
$var wire 1 " cout $end
$var reg 1 # a $end
$var reg 1 $ b $end
$var reg 1 % cin $end
$scope module gate $end
$var wire 1 # a $end
$var wire 1 $ b $end
$var wire 1 % cin $end
$var wire 1 " cout $end
$var wire 1 ! s $end
$upscope $end
$upscope $end
$enddefinitions $end
#0
$dumpvars
0%
0$
0#
0"
0!
$end
#10
1!
1%
#20
0%
1$
#30
1"
0!
1%
#40
0"
1!
0%
0$
1#
#50
1"
0!
1%
#60
0%
1$
#70
1!
1%
